{"5x5":{"id":"daily-2026-07-21-5x5","gridSize":"5x5","rows":5,"cols":5,"difficulty":"easy","grid":[["#","#","Y","S","W"],["#","A","R","#","O"],["#","L","#","D","R"],["P","O","S","E","Y"],["G","A","R","B","#"]],"walls":[[0,0],[0,1],[1,0],[1,3],[2,0],[2,2],[4,4]],"words":[{"word":"YES","length":3,"path":[[3,4],[3,3],[3,2]]},{"word":"GARB","length":4,"path":[[4,0],[4,1],[4,2],[4,3]]},{"word":"POLAR","length":5,"path":[[3,0],[3,1],[2,1],[1,1],[1,2]]},{"word":"DROWSY","length":6,"path":[[2,3],[2,4],[1,4],[0,4],[0,3],[0,2]]}],"date":"2026-07-21","type":"daily"},"6x6":{"id":"daily-2026-07-21-6x6","gridSize":"6x6","rows":6,"cols":6,"difficulty":"moderate","grid":[["E","#","I","N","U","R"],["N","O","U","#","N","#"],["S","T","R","T","#","#"],["#","P","#","E","G","R"],["#","R","#","C","T","O"],["#","O","T","E","#","F"]],"walls":[[0,1],[1,3],[1,5],[2,4],[2,5],[3,0],[3,2],[4,0],[4,2],[5,0],[5,4]],"words":[{"word":"RUN","length":3,"path":[[0,5],[0,4],[1,4]]},{"word":"RUIN","length":4,"path":[[2,2],[1,2],[0,2],[0,3]]},{"word":"STONE","length":5,"path":[[2,0],[2,1],[1,1],[1,0],[0,0]]},{"word":"FORGET","length":6,"path":[[5,5],[4,5],[3,5],[3,4],[3,3],[2,3]]},{"word":"PROTECT","length":7,"path":[[3,1],[4,1],[5,1],[5,2],[5,3],[4,3],[4,4]]}],"date":"2026-07-21","type":"daily"},"7x7":{"id":"daily-2026-07-21-7x7","gridSize":"7x7","rows":7,"cols":7,"difficulty":"medium","grid":[["#","E","D","#","O","T","U"],["#","L","#","#","#","#","A"],["#","T","I","#","R","A","I"],["A","#","T","N","E","#","N"],["R","T","#","#","#","#","Y"],["#","I","E","H","C","L","C"],["#","C","L","#","T","U","#"]],"walls":[[0,0],[0,3],[1,0],[1,2],[1,3],[1,4],[1,5],[2,0],[2,3],[3,1],[3,5],[4,2],[4,3],[4,4],[4,5],[5,0],[6,0],[6,3],[6,6]],"words":[{"word":"AUTO","length":4,"path":[[1,6],[0,6],[0,5],[0,4]]},{"word":"RAINY","length":5,"path":[[2,4],[2,5],[2,6],[3,6],[4,6]]},{"word":"CLUTCH","length":6,"path":[[5,6],[5,5],[6,5],[6,4],[5,4],[5,3]]},{"word":"ARTICLE","length":7,"path":[[3,0],[4,0],[4,1],[5,1],[6,1],[6,2],[5,2]]},{"word":"ENTITLED","length":8,"path":[[3,4],[3,3],[3,2],[2,2],[2,1],[1,1],[0,1],[0,2]]}],"date":"2026-07-21","type":"daily"},"8x8":{"id":"daily-2026-07-21-8x8","gridSize":"8x8","rows":8,"cols":8,"difficulty":"hard","grid":[["E","#","#","S","A","F","E","L"],["S","#","#","#","#","#","#","Y"],["C","R","#","U","O","F","R","A"],["O","E","D","N","#","#","#","J"],["R","S","#","#","#","#","#","S"],["T","T","R","#","C","#","#","T"],["E","#","A","T","I","#","#","A"],["D","#","#","E","G","#","E","V"]],"walls":[[0,1],[0,2],[1,1],[1,2],[1,3],[1,4],[1,5],[1,6],[2,2],[3,4],[3,5],[3,6],[4,2],[4,3],[4,4],[4,5],[4,6],[5,3],[5,5],[5,6],[6,1],[6,5],[6,6],[7,1],[7,2],[7,5]],"words":[{"word":"JAR","length":3,"path":[[3,7],[2,7],[2,6]]},{"word":"STAVE","length":5,"path":[[4,7],[5,7],[6,7],[7,7],[7,6]]},{"word":"SAFELY","length":6,"path":[[0,3],[0,4],[0,5],[0,6],[0,7],[1,7]]},{"word":"FOUNDER","length":7,"path":[[2,5],[2,4],[2,3],[3,3],[3,2],[3,1],[2,1]]},{"word":"ESCORTED","length":8,"path":[[0,0],[1,0],[2,0],[3,0],[4,0],[5,0],[6,0],[7,0]]},{"word":"STRATEGIC","length":9,"path":[[4,1],[5,1],[5,2],[6,2],[6,3],[7,3],[7,4],[6,4],[5,4]]}],"date":"2026-07-21","type":"daily"},"9x9":{"id":"daily-2026-07-21-9x9","gridSize":"9x9","rows":9,"cols":9,"difficulty":"expert","grid":[["#","I","N","G","#","A","R","L","#"],["N","D","#","T","S","E","Y","O","#"],["E","#","#","#","I","#","#","N","#"],["#","#","S","I","L","#","#","G","#"],["#","H","#","X","#","#","#","L","O"],["#","A","#","T","Y","#","#","#","G"],["#","N","#","T","#","#","#","#","A"],["#","D","O","U","#","#","T","I","R"],["#","#","#","#","#","M","H","#","#"]],"walls":[[0,0],[0,4],[0,8],[1,2],[1,8],[2,1],[2,2],[2,3],[2,5],[2,6],[2,8],[3,0],[3,1],[3,5],[3,6],[3,8],[4,0],[4,2],[4,4],[4,5],[4,6],[5,0],[5,2],[5,5],[5,6],[5,7],[6,0],[6,2],[6,4],[6,5],[6,6],[6,7],[7,0],[7,4],[7,5],[8,0],[8,1],[8,2],[8,3],[8,4],[8,7],[8,8]],"words":[{"word":"LIST","length":4,"path":[[3,4],[2,4],[1,4],[1,3]]},{"word":"SIXTY","length":5,"path":[[3,2],[3,3],[4,3],[5,3],[5,4]]},{"word":"ENDING","length":6,"path":[[2,0],[1,0],[1,1],[0,1],[0,2],[0,3]]},{"word":"HANDOUT","length":7,"path":[[4,1],[5,1],[6,1],[7,1],[7,2],[7,3],[6,3]]},{"word":"YEARLONG","length":8,"path":[[1,6],[1,5],[0,5],[0,6],[0,7],[1,7],[2,7],[3,7]]},{"word":"LOGARITHM","length":9,"path":[[4,7],[4,8],[5,8],[6,8],[7,8],[7,7],[7,6],[8,6],[8,5]]}],"date":"2026-07-21","type":"daily"},"10x10":{"id":"daily-2026-07-21-10x10","gridSize":"10x10","rows":10,"cols":10,"difficulty":"master","grid":[["#","F","R","#","F","A","S","#","#","#"],["#","#","E","I","G","#","H","#","#","#"],["#","#","#","#","H","#","I","O","N","S"],["#","P","K","O","T","#","#","#","#","#"],["#","E","#","W","#","#","#","#","#","#"],["#","E","#","I","O","#","A","C","#","#"],["S","T","#","L","#","#","R","#","#","#"],["#","#","#","Y","#","#","P","#","#","G"],["#","#","#","T","L","E","E","T","I","N"],["#","G","E","N","#","#","#","#","#","#"]],"walls":[[0,0],[0,3],[0,7],[0,8],[0,9],[1,0],[1,1],[1,5],[1,7],[1,8],[1,9],[2,0],[2,1],[2,2],[2,3],[2,5],[3,0],[3,5],[3,6],[3,7],[3,8],[3,9],[4,0],[4,2],[4,4],[4,5],[4,6],[4,7],[4,8],[4,9],[5,0],[5,2],[5,5],[5,8],[5,9],[6,2],[6,4],[6,5],[6,7],[6,8],[6,9],[7,0],[7,1],[7,2],[7,4],[7,5],[7,7],[7,8],[8,0],[8,1],[8,2],[9,0],[9,4],[9,5],[9,6],[9,7],[9,8],[9,9]],"words":[{"word":"WOK","length":3,"path":[[4,3],[3,3],[3,2]]},{"word":"OILY","length":4,"path":[[5,4],[5,3],[6,3],[7,3]]},{"word":"STEEP","length":5,"path":[[6,0],[6,1],[5,1],[4,1],[3,1]]},{"word":"GENTLE","length":6,"path":[[9,1],[9,2],[9,3],[8,3],[8,4],[8,5]]},{"word":"FREIGHT","length":7,"path":[[0,1],[0,2],[1,2],[1,3],[1,4],[2,4],[3,4]]},{"word":"FASHIONS","length":8,"path":[[0,4],[0,5],[0,6],[1,6],[2,6],[2,7],[2,8],[2,9]]},{"word":"CARPETING","length":9,"path":[[5,7],[5,6],[6,6],[7,6],[8,6],[8,7],[8,8],[8,9],[7,9]]}],"date":"2026-07-21","type":"daily"}}