{"5x5":{"id":"daily-2026-07-07-5x5","gridSize":"5x5","rows":5,"cols":5,"difficulty":"easy","grid":[["P","#","H","A","S"],["A","R","E","W","S"],["#","T","D","#","U"],["#","E","E","#","M"],["G","R","#","#","E"]],"walls":[[0,1],[2,0],[2,3],[3,0],[3,3],[4,2],[4,3]],"words":[{"word":"HEW","length":3,"path":[[0,2],[1,2],[1,3]]},{"word":"TRAP","length":4,"path":[[2,1],[1,1],[1,0],[0,0]]},{"word":"GREED","length":5,"path":[[4,0],[4,1],[3,1],[3,2],[2,2]]},{"word":"ASSUME","length":6,"path":[[0,3],[0,4],[1,4],[2,4],[3,4],[4,4]]}],"date":"2026-07-07","type":"daily"},"6x6":{"id":"daily-2026-07-07-6x6","gridSize":"6x6","rows":6,"cols":6,"difficulty":"moderate","grid":[["O","W","#","M","O","W"],["D","#","B","#","L","L"],["A","#","R","M","I","#"],["E","E","I","#","E","G"],["M","F","#","#","D","I"],["#","#","#","O","B","L"]],"walls":[[0,2],[1,1],[1,3],[2,1],[2,5],[3,3],[4,2],[4,3],[5,0],[5,1],[5,2]],"words":[{"word":"MOW","length":3,"path":[[0,3],[0,4],[0,5]]},{"word":"MILL","length":4,"path":[[2,3],[2,4],[1,4],[1,5]]},{"word":"BRIEF","length":5,"path":[[1,2],[2,2],[3,2],[3,1],[4,1]]},{"word":"MEADOW","length":6,"path":[[4,0],[3,0],[2,0],[1,0],[0,0],[0,1]]},{"word":"OBLIGED","length":7,"path":[[5,3],[5,4],[5,5],[4,5],[3,5],[3,4],[4,4]]}],"date":"2026-07-07","type":"daily"},"7x7":{"id":"daily-2026-07-07-7x7","gridSize":"7x7","rows":7,"cols":7,"difficulty":"medium","grid":[["A","S","R","#","#","#","M"],["L","#","E","V","#","#","U"],["#","F","#","E","R","D","N"],["O","L","T","#","#","A","#"],["O","O","L","H","E","N","#"],["R","C","#","C","#","#","#"],["#","#","#","A","E","L","B"]],"walls":[[0,3],[0,4],[0,5],[1,1],[1,4],[1,5],[2,0],[2,2],[3,3],[3,4],[3,6],[4,6],[5,2],[5,4],[5,5],[5,6],[6,0],[6,1],[6,2]],"words":[{"word":"COLT","length":4,"path":[[5,1],[4,1],[4,2],[3,2]]},{"word":"FLOOR","length":5,"path":[[2,1],[3,1],[3,0],[4,0],[5,0]]},{"word":"BLEACH","length":6,"path":[[6,6],[6,5],[6,4],[6,3],[5,3],[4,3]]},{"word":"MUNDANE","length":7,"path":[[0,6],[1,6],[2,6],[2,5],[3,5],[4,5],[4,4]]},{"word":"REVERSAL","length":8,"path":[[2,4],[2,3],[1,3],[1,2],[0,2],[0,1],[0,0],[1,0]]}],"date":"2026-07-07","type":"daily"},"8x8":{"id":"daily-2026-07-07-8x8","gridSize":"8x8","rows":8,"cols":8,"difficulty":"hard","grid":[["A","W","E","R","#","E","R","F"],["R","#","#","#","#","Q","#","#"],["D","G","U","D","#","U","E","#"],["I","N","N","#","D","#","N","#"],["#","#","M","P","R","#","T","#"],["#","#","A","R","A","P","O","#"],["E","C","C","T","#","#","E","L"],["L","N","A","#","#","#","#","#"]],"walls":[[0,4],[1,1],[1,2],[1,3],[1,4],[1,6],[1,7],[2,4],[2,7],[3,3],[3,5],[3,7],[4,0],[4,1],[4,5],[4,7],[5,0],[5,1],[5,7],[6,4],[6,5],[7,3],[7,4],[7,5],[7,6],[7,7]],"words":[{"word":"DUN","length":3,"path":[[2,3],[2,2],[3,2]]},{"word":"TRAMP","length":5,"path":[[6,3],[5,3],[5,2],[4,2],[4,3]]},{"word":"CANCEL","length":6,"path":[[6,2],[7,2],[7,1],[6,1],[6,0],[7,0]]},{"word":"LEOPARD","length":7,"path":[[6,7],[6,6],[5,6],[5,5],[5,4],[4,4],[3,4]]},{"word":"FREQUENT","length":8,"path":[[0,7],[0,6],[0,5],[1,5],[2,5],[2,6],[3,6],[4,6]]},{"word":"REWARDING","length":9,"path":[[0,3],[0,2],[0,1],[0,0],[1,0],[2,0],[3,0],[3,1],[2,1]]}],"date":"2026-07-07","type":"daily"},"9x9":{"id":"daily-2026-07-07-9x9","gridSize":"9x9","rows":9,"cols":9,"difficulty":"expert","grid":[["#","#","#","#","#","C","O","N","C"],["S","A","H","P","M","#","#","#","E"],["I","S","#","#","E","#","#","T","P"],["#","P","A","P","#","L","D","N","#"],["#","#","E","E","R","E","#","U","#"],["#","I","T","#","#","#","E","B","#"],["#","K","#","#","R","O","D","#","#"],["#","#","#","#","T","#","#","#","#"],["#","#","#","#","C","E","L","E","#"]],"walls":[[0,0],[0,1],[0,2],[0,3],[0,4],[1,5],[1,6],[1,7],[2,2],[2,3],[2,5],[2,6],[3,0],[3,4],[3,8],[4,0],[4,1],[4,6],[4,8],[5,0],[5,3],[5,4],[5,5],[5,8],[6,0],[6,2],[6,3],[6,7],[6,8],[7,0],[7,1],[7,2],[7,3],[7,5],[7,6],[7,7],[7,8],[8,0],[8,1],[8,2],[8,3],[8,8]],"words":[{"word":"KITE","length":4,"path":[[6,1],[5,1],[5,2],[4,2]]},{"word":"PAPER","length":5,"path":[[3,1],[3,2],[3,3],[4,3],[4,4]]},{"word":"BUNDLE","length":6,"path":[[5,7],[4,7],[3,7],[3,6],[3,5],[4,5]]},{"word":"CONCEPT","length":7,"path":[[0,5],[0,6],[0,7],[0,8],[1,8],[2,8],[2,7]]},{"word":"EMPHASIS","length":8,"path":[[2,4],[1,4],[1,3],[1,2],[1,1],[1,0],[2,0],[2,1]]},{"word":"ELECTRODE","length":9,"path":[[8,7],[8,6],[8,5],[8,4],[7,4],[6,4],[6,5],[6,6],[5,6]]}],"date":"2026-07-07","type":"daily"},"10x10":{"id":"daily-2026-07-07-10x10","gridSize":"10x10","rows":10,"cols":10,"difficulty":"master","grid":[["#","I","N","S","#","#","#","#","T","#"],["#","#","#","T","A","N","T","R","A","T"],["#","#","E","R","#","#","#","#","#","I"],["#","#","T","#","#","#","#","L","G","N"],["#","E","S","#","#","Y","R","O","#","U"],["#","M","#","#","#","#","#","L","#","#"],["S","E","D","E","N","#","#","A","E","#"],["#","#","#","#","I","#","#","#","P","#"],["#","#","#","#","L","#","#","A","P","#"],["#","S","I","D","E","#","#","#","#","#"]],"walls":[[0,0],[0,4],[0,5],[0,6],[0,7],[0,9],[1,0],[1,1],[1,2],[2,0],[2,1],[2,4],[2,5],[2,6],[2,7],[2,8],[3,0],[3,1],[3,3],[3,4],[3,5],[3,6],[4,0],[4,3],[4,4],[4,8],[5,0],[5,2],[5,3],[5,4],[5,5],[5,6],[5,8],[5,9],[6,5],[6,6],[6,9],[7,0],[7,1],[7,2],[7,3],[7,5],[7,6],[7,7],[7,9],[8,0],[8,1],[8,2],[8,3],[8,5],[8,6],[8,9],[9,0],[9,5],[9,6],[9,7],[9,8],[9,9]],"words":[{"word":"TAR","length":3,"path":[[0,8],[1,8],[1,7]]},{"word":"UNIT","length":4,"path":[[4,9],[3,9],[2,9],[1,9]]},{"word":"GLORY","length":5,"path":[[3,8],[3,7],[4,7],[4,6],[4,5]]},{"word":"APPEAL","length":6,"path":[[8,7],[8,8],[7,8],[6,8],[6,7],[5,7]]},{"word":"INSTANT","length":7,"path":[[0,1],[0,2],[0,3],[1,3],[1,4],[1,5],[1,6]]},{"word":"SEMESTER","length":8,"path":[[6,0],[6,1],[5,1],[4,1],[4,2],[3,2],[2,2],[2,3]]},{"word":"SIDELINED","length":9,"path":[[9,1],[9,2],[9,3],[9,4],[8,4],[7,4],[6,4],[6,3],[6,2]]}],"date":"2026-07-07","type":"daily"}}